Workbook

Sheet Summary
A1: FX Funnel + Investing Engine — Summary Dashboard
A2: Outputs (green) are driven by the Assumptions sheet.
A4: 3-YEAR P&L
B5: Year 1 | C5: Year 2 | D5: Year 3
A6: FX + card revenue | B6: =SUM('Monthly P&L'!D4:D15)+SUM('Monthly P&L'!E4:E15) | C6: =SUM('Monthly P&L'!D16:D27)+SUM('Monthly P&L'!E16:E27) | D6: =SUM('Monthly P&L'!D28:D39)+SUM('Monthly P&L'!E28:E39)
A7: Investing revenue | B7: =SUM('Monthly P&L'!I4:I15)+SUM('Monthly P&L'!J4:J15) | C7: =SUM('Monthly P&L'!I16:I27)+SUM('Monthly P&L'!J16:J27) | D7: =SUM('Monthly P&L'!I28:I39)+SUM('Monthly P&L'!J28:J39)
A8: Total revenue | B8: =SUM('Monthly P&L'!K4:K15) | C8: =SUM('Monthly P&L'!K16:K27) | D8: =SUM('Monthly P&L'!K28:K39)
A9: Variable cost | B9: =SUM('Monthly P&L'!L4:L15) | C9: =SUM('Monthly P&L'!L16:L27) | D9: =SUM('Monthly P&L'!L28:L39)
A10: Fixed cost | B10: =SUM('Monthly P&L'!M4:M15) | C10: =SUM('Monthly P&L'!M16:M27) | D10: =SUM('Monthly P&L'!M28:M39)
A11: Operating profit | B11: =SUM('Monthly P&L'!N4:N15) | C11: =SUM('Monthly P&L'!N16:N27) | D11: =SUM('Monthly P&L'!N28:N39)
A12: Investing % of revenue | B12: =B7/B8 | C12: =C7/C8 | D12: =D7/D8
A13: Operating margin | B13: =B11/B8 | C13: =C11/C8 | D13: =D11/D8
A15: KEY METRICS
A16: Active customers — end of Y1 | B16: ='Monthly P&L'!C15
A17: Active customers — end of Y3 | B17: ='Monthly P&L'!C39
A18: Investing clients — end of Y3 | B18: ='Monthly P&L'!F39
A19: AUM balance — end of Y3 | B19: ='Monthly P&L'!H39
A20: First profitable month | B20: =IFERROR(MATCH(1,'Monthly P&L'!P4:P39,0),"not in 36mo")
A21: Max cumulative burn (capital need) | B21: =MIN('Monthly P&L'!O4:O39)
A22: Cumulative cash @ month 36 | B22: ='Monthly P&L'!O39
A23: FX-only LTV / CAC | B23: ='Unit Economics'!B12
A24: Investing LTV vs FX-only | B24: ='Unit Economics'!B20
A26: Watch ‘Investing % of revenue’ climb Y1→Y3: that's the funnel→engine thesis working.

Sheet Assumptions
A1: FX / Neobank + Investing — Model Assumptions
A2: Edit ONLY the yellow cells. Everything else recomputes.
A4: FX / REMITTANCE REVENUE (the funnel)
A5: Take rate (visible fee) | B5: 0.01 | C5: headline ~1%
A6: FX spread | B6: 0.005 | C6: hidden margin in the rate
A7: Card interchange (net to us) | B7: 0.008 | C7: share of card spend
A9: INVESTING / RIA REVENUE (the engine)
A10: % of active custs → managed-acct clients | B10: 0.08 | C10: FX→investing conversion
A11: Initial deposit on conversion ($) | B11: 2000 | C11: seed into US managed acct
A12: Monthly contribution / investing client ($) | B12: 150 | C12: retirement-style DCA
A13: Annual AUM fee | B13: 0.0075 | C13: 0.5–1% typical
A14: Assumed annual return on AUM | B14: 0.07 | C14: for balance growth only
A15: Investing client lifetime (years) | B15: 6 | C15: they churn FAR less than FX users
A17: VARIABLE COSTS
A18: On/off-ramp + stablecoin/FX cost | B18: 0.007 | C18: cross-border leg; applies to FX & inflows
A19: KYC cost per new customer | B19: 1.5 | C19: per onboarding check
A20: Support cost / active cust / mo | B20: 0.5
A21: CAC per new customer | B21: 25 | C21: acquisition
A23: CUSTOMER BEHAVIOR (FX side)
A24: Avg FX ticket ($) | B24: 800
A25: FX txns / active cust / mo | B25: 1.5
A26: Card spend / active cust / mo ($) | B26: 300
A27: Monthly churn (FX cust) | B27: 0.04 | C27: investing clients churn far less
A29: GROWTH
A30: New customers — month 1 | B30: 100
A31: MoM growth in new customers | B31: 0.1
A33: FIXED ANNUAL COSTS
A34: BSA/AML officer + compliance tooling | B34: 90000 | C34: hire #1
A35: RIA / investing compliance + custodian | B35: 60000 | C35: CCO, RIA, custody integration
A36: Legal / regulatory ongoing | B36: 40000
A37: Engineering / product | B37: 120000
A38: Substance (local staff/office in op jx) | B38: 60000 | C38: PR needs 8 staff!
A39: Other G&A | B39: 30000
A40: TOTAL FIXED / YEAR | B40: =SUM(B34:B39)

Sheet Unit Economics
A1: Unit Economics — FX customer vs Investing client
A3: FX / REMITTANCE CUSTOMER
A4: FX revenue / cust / mo | B4: =Assumptions!$B$24*Assumptions!$B$25*(Assumptions!$B$5+Assumptions!$B$6)
A5: Card revenue / cust / mo | B5: =Assumptions!$B$26*Assumptions!$B$7
A6: ARPU / cust / mo | B6: =B4+B5
A7: Variable cost / cust / mo | B7: =Assumptions!$B$24*Assumptions!$B$25*Assumptions!$B$18+Assumptions!$B$20
A8: Gross profit / cust / mo | B8: =B6-B7
A9: Acquisition cost (CAC+KYC) | B9: =Assumptions!$B$21+Assumptions!$B$19
A10: Avg lifetime (mo) | B10: =1/Assumptions!$B$27
A11: LTV (FX-only) | B11: =B8/Assumptions!$B$27
A12: LTV / CAC (FX-only) | B12: =B11/B9
A13: CAC payback (months) | B13: =B9/B8
A15: INVESTING CLIENT (the engine)
A16: Avg AUM balance over client life | B16: =Assumptions!$B$11+(Assumptions!$B$12*12*Assumptions!$B$15)/2
A17: AUM fee / yr (at avg balance) | B17: =B16*Assumptions!$B$13
A18: Contribution FX margin / yr | B18: =12*Assumptions!$B$12*(Assumptions!$B$5+Assumptions!$B$6-Assumptions!$B$18)
A19: Investing client LTV (over lifetime) | B19: =(B17+B18)*Assumptions!$B$15
A20: Investing LTV vs FX-only LTV | B20: =B19/B11
A22: LTV understates investing: AUM compounds with contributions + market return.
A23: The point: an investing client is worth a multiple of an FX-only one — that's the thesis.

Sheet Corridors
A1: Corridor Competitiveness — you compete vs GOVERNMENT TAX
A2: ‘Our all-in’ = gov tax + our spread + our fee. Yellow = editable.
A4: Corridor / lane | B4: Gov tax | C4: Our spread+fee | D4: Our all-in | E4: Incumbent all-in | F4: Customer saving (pp) | G4: Win?
A5: Brazil — investment abroad (1.10% IOF) ← our lane | B5: 0.011 | C5: =Assumptions!$B$5+Assumptions!$B$6 | D5: =B5+C5 | E5: 0.03 | F5: =E5-D5 | G5: =IF(F5>=0.01,"YES","weak")
A6: Brazil — cash/card FX abroad | B6: 0.035 | C6: =Assumptions!$B$5+Assumptions!$B$6 | D6: =B6+C6 | E6: 0.065 | F6: =E6-D6 | G6: =IF(F6>=0.01,"YES","weak")
A7: Into Brazil — diff-owner remittance | B7: 0.0038 | C7: =Assumptions!$B$5+Assumptions!$B$6 | D7: =B7+C7 | E7: 0.06 | F7: =E7-D7 | G7: =IF(F7>=0.01,"YES","weak")
A8: Argentina — individual USD | B8: 0 | C8: =Assumptions!$B$5+Assumptions!$B$6 | D8: =B8+C8 | E8: 0.03 | F8: =E8-D8 | G8: =IF(F8>=0.01,"YES","weak")
A9: US → Mexico remittance | B9: 0 | C9: =Assumptions!$B$5+Assumptions!$B$6 | D9: =B9+C9 | E9: 0.045 | F9: =E9-D9 | G9: =IF(F9>=0.01,"YES","weak")
A10: EU/Asia → LatAm inbound | B10: 0 | C10: =Assumptions!$B$5+Assumptions!$B$6 | D10: =B10+C10 | E10: 0.05 | F10: =E10-D10 | G10: =IF(F10>=0.01,"YES","weak")

Sheet Monthly P&L
A1: Monthly P&L — 36 months (FX funnel + investing engine)
A3: Month | B3: New cust | C3: Active cust | D3: FX rev | E3: Card rev | F3: Inv clients | G3: AUM inflow | H3: AUM balance | I3: AUM rev | J3: Inflow FX rev | K3: Total rev | L3: Variable cost | M3: Fixed | N3: Op profit | O3: Cumulative | P3: Profit?
A4: 1 | B4: =Assumptions!$B$30 | C4: =B4 | D4: =C4*Assumptions!$B$24*Assumptions!$B$25*(Assumptions!$B$5+Assumptions!$B$6) | E4: =C4*Assumptions!$B$26*Assumptions!$B$7 | F4: =C4*Assumptions!$B$10 | G4: =F4*Assumptions!$B$11+F4*Assumptions!$B$12 | H4: =G4 | I4: =H4*Assumptions!$B$13/12 | J4: =G4*(Assumptions!$B$5+Assumptions!$B$6) | K4: =D4+E4+I4+J4 | L4: =C4*(Assumptions!$B$24*Assumptions!$B$25*Assumptions!$B$18+Assumptions!$B$20)+B4*(Assumptions!$B$21+Assumptions!$B$19)+G4*Assumptions!$B$18 | M4: =Assumptions!$B$40/12 | N4: =K4-L4-M4 | O4: =N4 | P4: =IF(N4>0,1,0)
A5: 2 | B5: =B4*(1+Assumptions!$B$31) | C5: =C4*(1-Assumptions!$B$27)+B5 | D5: =C5*Assumptions!$B$24*Assumptions!$B$25*(Assumptions!$B$5+Assumptions!$B$6) | E5: =C5*Assumptions!$B$26*Assumptions!$B$7 | F5: =C5*Assumptions!$B$10 | G5: =MAX(F5-F4,0)*Assumptions!$B$11+F5*Assumptions!$B$12 | H5: =H4*(1+Assumptions!$B$14/12)+G5 | I5: =H5*Assumptions!$B$13/12 | J5: =G5*(Assumptions!$B$5+Assumptions!$B$6) | K5: =D5+E5+I5+J5 | L5: =C5*(Assumptions!$B$24*Assumptions!$B$25*Assumptions!$B$18+Assumptions!$B$20)+B5*(Assumptions!$B$21+Assumptions!$B$19)+G5*Assumptions!$B$18 | M5: =Assumptions!$B$40/12 | N5: =K5-L5-M5 | O5: =O4+N5 | P5: =IF(N5>0,1,0)
A6: 3 | B6: =B5*(1+Assumptions!$B$31) | C6: =C5*(1-Assumptions!$B$27)+B6 | D6: =C6*Assumptions!$B$24*Assumptions!$B$25*(Assumptions!$B$5+Assumptions!$B$6) | E6: =C6*Assumptions!$B$26*Assumptions!$B$7 | F6: =C6*Assumptions!$B$10 | G6: =MAX(F6-F5,0)*Assumptions!$B$11+F6*Assumptions!$B$12 | H6: =H5*(1+Assumptions!$B$14/12)+G6 | I6: =H6*Assumptions!$B$13/12 | J6: =G6*(Assumptions!$B$5+Assumptions!$B$6) | K6: =D6+E6+I6+J6 | L6: =C6*(Assumptions!$B$24*Assumptions!$B$25*Assumptions!$B$18+Assumptions!$B$20)+B6*(Assumptions!$B$21+Assumptions!$B$19)+G6*Assumptions!$B$18 | M6: =Assumptions!$B$40/12 | N6: =K6-L6-M6 | O6: =O5+N6 | P6: =IF(N6>0,1,0)
A7: 4 | B7: =B6*(1+Assumptions!$B$31) | C7: =C6*(1-Assumptions!$B$27)+B7 | D7: =C7*Assumptions!$B$24*Assumptions!$B$25*(Assumptions!$B$5+Assumptions!$B$6) | E7: =C7*Assumptions!$B$26*Assumptions!$B$7 | F7: =C7*Assumptions!$B$10 | G7: =MAX(F7-F6,0)*Assumptions!$B$11+F7*Assumptions!$B$12 | H7: =H6*(1+Assumptions!$B$14/12)+G7 | I7: =H7*Assumptions!$B$13/12 | J7: =G7*(Assumptions!$B$5+Assumptions!$B$6) | K7: =D7+E7+I7+J7 | L7: =C7*(Assumptions!$B$24*Assumptions!$B$25*Assumptions!$B$18+Assumptions!$B$20)+B7*(Assumptions!$B$21+Assumptions!$B$19)+G7*Assumptions!$B$18 | M7: =Assumptions!$B$40/12 | N7: =K7-L7-M7 | O7: =O6+N7 | P7: =IF(N7>0,1,0)
A8: 5 | B8: =B7*(1+Assumptions!$B$31) | C8: =C7*(1-Assumptions!$B$27)+B8 | D8: =C8*Assumptions!$B$24*Assumptions!$B$25*(Assumptions!$B$5+Assumptions!$B$6) | E8: =C8*Assumptions!$B$26*Assumptions!$B$7 | F8: =C8*Assumptions!$B$10 | G8: =MAX(F8-F7,0)*Assumptions!$B$11+F8*Assumptions!$B$12 | H8: =H7*(1+Assumptions!$B$14/12)+G8 | I8: =H8*Assumptions!$B$13/12 | J8: =G8*(Assumptions!$B$5+Assumptions!$B$6) | K8: =D8+E8+I8+J8 | L8: =C8*(Assumptions!$B$24*Assumptions!$B$25*Assumptions!$B$18+Assumptions!$B$20)+B8*(Assumptions!$B$21+Assumptions!$B$19)+G8*Assumptions!$B$18 | M8: =Assumptions!$B$40/12 | N8: =K8-L8-M8 | O8: =O7+N8 | P8: =IF(N8>0,1,0)
A9: 6 | B9: =B8*(1+Assumptions!$B$31) | C9: =C8*(1-Assumptions!$B$27)+B9 | D9: =C9*Assumptions!$B$24*Assumptions!$B$25*(Assumptions!$B$5+Assumptions!$B$6) | E9: =C9*Assumptions!$B$26*Assumptions!$B$7 | F9: =C9*Assumptions!$B$10 | G9: =MAX(F9-F8,0)*Assumptions!$B$11+F9*Assumptions!$B$12 | H9: =H8*(1+Assumptions!$B$14/12)+G9 | I9: =H9*Assumptions!$B$13/12 | J9: =G9*(Assumptions!$B$5+Assumptions!$B$6) | K9: =D9+E9+I9+J9 | L9: =C9*(Assumptions!$B$24*Assumptions!$B$25*Assumptions!$B$18+Assumptions!$B$20)+B9*(Assumptions!$B$21+Assumptions!$B$19)+G9*Assumptions!$B$18 | M9: =Assumptions!$B$40/12 | N9: =K9-L9-M9 | O9: =O8+N9 | P9: =IF(N9>0,1,0)
A10: 7 | B10: =B9*(1+Assumptions!$B$31) | C10: =C9*(1-Assumptions!$B$27)+B10 | D10: =C10*Assumptions!$B$24*Assumptions!$B$25*(Assumptions!$B$5+Assumptions!$B$6) | E10: =C10*Assumptions!$B$26*Assumptions!$B$7 | F10: =C10*Assumptions!$B$10 | G10: =MAX(F10-F9,0)*Assumptions!$B$11+F10*Assumptions!$B$12 | H10: =H9*(1+Assumptions!$B$14/12)+G10 | I10: =H10*Assumptions!$B$13/12 | J10: =G10*(Assumptions!$B$5+Assumptions!$B$6) | K10: =D10+E10+I10+J10 | L10: =C10*(Assumptions!$B$24*Assumptions!$B$25*Assumptions!$B$18+Assumptions!$B$20)+B10*(Assumptions!$B$21+Assumptions!$B$19)+G10*Assumptions!$B$18 | M10: =Assumptions!$B$40/12 | N10: =K10-L10-M10 | O10: =O9+N10 | P10: =IF(N10>0,1,0)
A11: 8 | B11: =B10*(1+Assumptions!$B$31) | C11: =C10*(1-Assumptions!$B$27)+B11 | D11: =C11*Assumptions!$B$24*Assumptions!$B$25*(Assumptions!$B$5+Assumptions!$B$6) | E11: =C11*Assumptions!$B$26*Assumptions!$B$7 | F11: =C11*Assumptions!$B$10 | G11: =MAX(F11-F10,0)*Assumptions!$B$11+F11*Assumptions!$B$12 | H11: =H10*(1+Assumptions!$B$14/12)+G11 | I11: =H11*Assumptions!$B$13/12 | J11: =G11*(Assumptions!$B$5+Assumptions!$B$6) | K11: =D11+E11+I11+J11 | L11: =C11*(Assumptions!$B$24*Assumptions!$B$25*Assumptions!$B$18+Assumptions!$B$20)+B11*(Assumptions!$B$21+Assumptions!$B$19)+G11*Assumptions!$B$18 | M11: =Assumptions!$B$40/12 | N11: =K11-L11-M11 | O11: =O10+N11 | P11: =IF(N11>0,1,0)
A12: 9 | B12: =B11*(1+Assumptions!$B$31) | C12: =C11*(1-Assumptions!$B$27)+B12 | D12: =C12*Assumptions!$B$24*Assumptions!$B$25*(Assumptions!$B$5+Assumptions!$B$6) | E12: =C12*Assumptions!$B$26*Assumptions!$B$7 | F12: =C12*Assumptions!$B$10 | G12: =MAX(F12-F11,0)*Assumptions!$B$11+F12*Assumptions!$B$12 | H12: =H11*(1+Assumptions!$B$14/12)+G12 | I12: =H12*Assumptions!$B$13/12 | J12: =G12*(Assumptions!$B$5+Assumptions!$B$6) | K12: =D12+E12+I12+J12 | L12: =C12*(Assumptions!$B$24*Assumptions!$B$25*Assumptions!$B$18+Assumptions!$B$20)+B12*(Assumptions!$B$21+Assumptions!$B$19)+G12*Assumptions!$B$18 | M12: =Assumptions!$B$40/12 | N12: =K12-L12-M12 | O12: =O11+N12 | P12: =IF(N12>0,1,0)
A13: 10 | B13: =B12*(1+Assumptions!$B$31) | C13: =C12*(1-Assumptions!$B$27)+B13 | D13: =C13*Assumptions!$B$24*Assumptions!$B$25*(Assumptions!$B$5+Assumptions!$B$6) | E13: =C13*Assumptions!$B$26*Assumptions!$B$7 | F13: =C13*Assumptions!$B$10 | G13: =MAX(F13-F12,0)*Assumptions!$B$11+F13*Assumptions!$B$12 | H13: =H12*(1+Assumptions!$B$14/12)+G13 | I13: =H13*Assumptions!$B$13/12 | J13: =G13*(Assumptions!$B$5+Assumptions!$B$6) | K13: =D13+E13+I13+J13 | L13: =C13*(Assumptions!$B$24*Assumptions!$B$25*Assumptions!$B$18+Assumptions!$B$20)+B13*(Assumptions!$B$21+Assumptions!$B$19)+G13*Assumptions!$B$18 | M13: =Assumptions!$B$40/12 | N13: =K13-L13-M13 | O13: =O12+N13 | P13: =IF(N13>0,1,0)
A14: 11 | B14: =B13*(1+Assumptions!$B$31) | C14: =C13*(1-Assumptions!$B$27)+B14 | D14: =C14*Assumptions!$B$24*Assumptions!$B$25*(Assumptions!$B$5+Assumptions!$B$6) | E14: =C14*Assumptions!$B$26*Assumptions!$B$7 | F14: =C14*Assumptions!$B$10 | G14: =MAX(F14-F13,0)*Assumptions!$B$11+F14*Assumptions!$B$12 | H14: =H13*(1+Assumptions!$B$14/12)+G14 | I14: =H14*Assumptions!$B$13/12 | J14: =G14*(Assumptions!$B$5+Assumptions!$B$6) | K14: =D14+E14+I14+J14 | L14: =C14*(Assumptions!$B$24*Assumptions!$B$25*Assumptions!$B$18+Assumptions!$B$20)+B14*(Assumptions!$B$21+Assumptions!$B$19)+G14*Assumptions!$B$18 | M14: =Assumptions!$B$40/12 | N14: =K14-L14-M14 | O14: =O13+N14 | P14: =IF(N14>0,1,0)
A15: 12 | B15: =B14*(1+Assumptions!$B$31) | C15: =C14*(1-Assumptions!$B$27)+B15 | D15: =C15*Assumptions!$B$24*Assumptions!$B$25*(Assumptions!$B$5+Assumptions!$B$6) | E15: =C15*Assumptions!$B$26*Assumptions!$B$7 | F15: =C15*Assumptions!$B$10 | G15: =MAX(F15-F14,0)*Assumptions!$B$11+F15*Assumptions!$B$12 | H15: =H14*(1+Assumptions!$B$14/12)+G15 | I15: =H15*Assumptions!$B$13/12 | J15: =G15*(Assumptions!$B$5+Assumptions!$B$6) | K15: =D15+E15+I15+J15 | L15: =C15*(Assumptions!$B$24*Assumptions!$B$25*Assumptions!$B$18+Assumptions!$B$20)+B15*(Assumptions!$B$21+Assumptions!$B$19)+G15*Assumptions!$B$18 | M15: =Assumptions!$B$40/12 | N15: =K15-L15-M15 | O15: =O14+N15 | P15: =IF(N15>0,1,0)
A16: 13 | B16: =B15*(1+Assumptions!$B$31) | C16: =C15*(1-Assumptions!$B$27)+B16 | D16: =C16*Assumptions!$B$24*Assumptions!$B$25*(Assumptions!$B$5+Assumptions!$B$6) | E16: =C16*Assumptions!$B$26*Assumptions!$B$7 | F16: =C16*Assumptions!$B$10 | G16: =MAX(F16-F15,0)*Assumptions!$B$11+F16*Assumptions!$B$12 | H16: =H15*(1+Assumptions!$B$14/12)+G16 | I16: =H16*Assumptions!$B$13/12 | J16: =G16*(Assumptions!$B$5+Assumptions!$B$6) | K16: =D16+E16+I16+J16 | L16: =C16*(Assumptions!$B$24*Assumptions!$B$25*Assumptions!$B$18+Assumptions!$B$20)+B16*(Assumptions!$B$21+Assumptions!$B$19)+G16*Assumptions!$B$18 | M16: =Assumptions!$B$40/12 | N16: =K16-L16-M16 | O16: =O15+N16 | P16: =IF(N16>0,1,0)
... A39: 36 | B39: =B38*(1+Assumptions!$B$31) | C39: =C38*(1-Assumptions!$B$27)+B39 | D39: =C39*Assumptions!$B$24*Assumptions!$B$25*(Assumptions!$B$5+Assumptions!$B$6) | E39: =C39*Assumptions!$B$26*Assumptions!$B$7 | F39: =C39*Assumptions!$B$10 | G39: =MAX(F39-F38,0)*Assumptions!$B$11+F39*Assumptions!$B$12 | H39: =H38*(1+Assumptions!$B$14/12)+G39 | I39: =H39*Assumptions!$B$13/12 | J39: =G39*(Assumptions!$B$5+Assumptions!$B$6) | K39: =D39+E39+I39+J39 | L39: =C39*(Assumptions!$B$24*Assumptions!$B$25*Assumptions!$B$18+Assumptions!$B$20)+B39*(Assumptions!$B$21+Assumptions!$B$19)+G39*Assumptions!$B$18 | M39: =Assumptions!$B$40/12 | N39: =K39-L39-M39 | O39: =O38+N39 | P39: =IF(N39>0,1,0)

Sheet VPN (separate)
A1: VPN — Separate Entity P&L (do not blend)
A3: INPUTS
A4: Price / sub / month | B4: 6
A5: Merchant-of-Record fee | B5: 0.05 | C5: offloads VAT/PCI/chargebacks
A6: CAC per subscriber | B6: 12
A7: Monthly churn | B7: 0.05
A8: Server/infra cost / sub / mo | B8: 1.2
A9: New subs — month 1 | B9: 80
A10: MoM growth in new subs | B10: 0.08
A11: Fixed annual cost (eng/audit/legal) | B11: 60000
A13: 3-YEAR P&L (live)
A14: Month | B14: New subs | C14: Active subs | D14: Net revenue | E14: Variable cost | F14: Fixed | G14: Op profit | H14: Cumulative
A15: 1 | B15: ='VPN (separate)'!$B$9 | C15: =B15 | D15: =C15*'VPN (separate)'!$B$4*(1-'VPN (separate)'!$B$5) | E15: =C15*'VPN (separate)'!$B$8+B15*'VPN (separate)'!$B$6 | F15: ='VPN (separate)'!$B$11/12 | G15: =D15-E15-F15 | H15: =G15
A16: 2 | B16: =B15*(1+'VPN (separate)'!$B$10) | C16: =C15*(1-'VPN (separate)'!$B$7)+B16 | D16: =C16*'VPN (separate)'!$B$4*(1-'VPN (separate)'!$B$5) | E16: =C16*'VPN (separate)'!$B$8+B16*'VPN (separate)'!$B$6 | F16: ='VPN (separate)'!$B$11/12 | G16: =D16-E16-F16 | H16: =H15+G16
A17: 3 | B17: =B16*(1+'VPN (separate)'!$B$10) | C17: =C16*(1-'VPN (separate)'!$B$7)+B17 | D17: =C17*'VPN (separate)'!$B$4*(1-'VPN (separate)'!$B$5) | E17: =C17*'VPN (separate)'!$B$8+B17*'VPN (separate)'!$B$6 | F17: ='VPN (separate)'!$B$11/12 | G17: =D17-E17-F17 | H17: =H16+G17
A18: 4 | B18: =B17*(1+'VPN (separate)'!$B$10) | C18: =C17*(1-'VPN (separate)'!$B$7)+B18 | D18: =C18*'VPN (separate)'!$B$4*(1-'VPN (separate)'!$B$5) | E18: =C18*'VPN (separate)'!$B$8+B18*'VPN (separate)'!$B$6 | F18: ='VPN (separate)'!$B$11/12 | G18: =D18-E18-F18 | H18: =H17+G18
A19: 5 | B19: =B18*(1+'VPN (separate)'!$B$10) | C19: =C18*(1-'VPN (separate)'!$B$7)+B19 | D19: =C19*'VPN (separate)'!$B$4*(1-'VPN (separate)'!$B$5) | E19: =C19*'VPN (separate)'!$B$8+B19*'VPN (separate)'!$B$6 | F19: ='VPN (separate)'!$B$11/12 | G19: =D19-E19-F19 | H19: =H18+G19
A20: 6 | B20: =B19*(1+'VPN (separate)'!$B$10) | C20: =C19*(1-'VPN (separate)'!$B$7)+B20 | D20: =C20*'VPN (separate)'!$B$4*(1-'VPN (separate)'!$B$5) | E20: =C20*'VPN (separate)'!$B$8+B20*'VPN (separate)'!$B$6 | F20: ='VPN (separate)'!$B$11/12 | G20: =D20-E20-F20 | H20: =H19+G20
A21: 7 | B21: =B20*(1+'VPN (separate)'!$B$10) | C21: =C20*(1-'VPN (separate)'!$B$7)+B21 | D21: =C21*'VPN (separate)'!$B$4*(1-'VPN (separate)'!$B$5) | E21: =C21*'VPN (separate)'!$B$8+B21*'VPN (separate)'!$B$6 | F21: ='VPN (separate)'!$B$11/12 | G21: =D21-E21-F21 | H21: =H20+G21
A22: 8 | B22: =B21*(1+'VPN (separate)'!$B$10) | C22: =C21*(1-'VPN (separate)'!$B$7)+B22 | D22: =C22*'VPN (separate)'!$B$4*(1-'VPN (separate)'!$B$5) | E22: =C22*'VPN (separate)'!$B$8+B22*'VPN (separate)'!$B$6 | F22: ='VPN (separate)'!$B$11/12 | G22: =D22-E22-F22 | H22: =H21+G22
A23: 9 | B23: =B22*(1+'VPN (separate)'!$B$10) | C23: =C22*(1-'VPN (separate)'!$B$7)+B23 | D23: =C23*'VPN (separate)'!$B$4*(1-'VPN (separate)'!$B$5) | E23: =C23*'VPN (separate)'!$B$8+B23*'VPN (separate)'!$B$6 | F23: ='VPN (separate)'!$B$11/12 | G23: =D23-E23-F23 | H23: =H22+G23
A24: 10 | B24: =B23*(1+'VPN (separate)'!$B$10) | C24: =C23*(1-'VPN (separate)'!$B$7)+B24 | D24: =C24*'VPN (separate)'!$B$4*(1-'VPN (separate)'!$B$5) | E24: =C24*'VPN (separate)'!$B$8+B24*'VPN (separate)'!$B$6 | F24: ='VPN (separate)'!$B$11/12 | G24: =D24-E24-F24 | H24: =H23+G24
A25: 11 | B25: =B24*(1+'VPN (separate)'!$B$10) | C25: =C24*(1-'VPN (separate)'!$B$7)+B25 | D25: =C25*'VPN (separate)'!$B$4*(1-'VPN (separate)'!$B$5) | E25: =C25*'VPN (separate)'!$B$8+B25*'VPN (separate)'!$B$6 | F25: ='VPN (separate)'!$B$11/12 | G25: =D25-E25-F25 | H25: =H24+G25
A26: 12 | B26: =B25*(1+'VPN (separate)'!$B$10) | C26: =C25*(1-'VPN (separate)'!$B$7)+B26 | D26: =C26*'VPN (separate)'!$B$4*(1-'VPN (separate)'!$B$5) | E26: =C26*'VPN (separate)'!$B$8+B26*'VPN (separate)'!$B$6 | F26: ='VPN (separate)'!$B$11/12 | G26: =D26-E26-F26 | H26: =H25+G26
A27: 13 | B27: =B26*(1+'VPN (separate)'!$B$10) | C27: =C26*(1-'VPN (separate)'!$B$7)+B27 | D27: =C27*'VPN (separate)'!$B$4*(1-'VPN (separate)'!$B$5) | E27: =C27*'VPN (separate)'!$B$8+B27*'VPN (separate)'!$B$6 | F27: ='VPN (separate)'!$B$11/12 | G27: =D27-E27-F27 | H27: =H26+G27
... A50: 36 | B50: =B49*(1+'VPN (separate)'!$B$10) | C50: =C49*(1-'VPN (separate)'!$B$7)+B50 | D50: =C50*'VPN (separate)'!$B$4*(1-'VPN (separate)'!$B$5) | E50: =C50*'VPN (separate)'!$B$8+B50*'VPN (separate)'!$B$6 | F50: ='VPN (separate)'!$B$11/12 | G50: =D50-E50-F50 | H50: =H49+G50
A52: Year-1 op profit | B52: =SUM(G15:G26)
A53: Year-3 op profit | B53: =SUM(G39:G50)
